{
    "ltm_context": {
        "injection_location": "BEFORE_NORMAL_CONTEXT",
        "memory_context_template": "{name2}'s memory log:\n{all_memories}\nDuring conversations between {name1} and {name2}, {name2} will try to remember the memory described above and naturally integrate it with the conversation.",
        "memory_template": "{time_difference}, {memory_name} said:\n\"{memory_message}\""
    },
    "ltm_writes": {
        "min_message_length": 100
    },
    "ltm_reads": {
        "max_cosine_distance": 0.60,
        "num_memories_to_fetch": 2,
        "memory_length_cutoff_in_chars": 1000
    }
}
