{
    "base_path": "models",
    "model_path": "xttsv2_2.0.2",
    "files_to_download": {
        "LICENSE.txt": "https://huggingface.co/coqui/XTTS-v2/resolve/v2.0.2/LICENSE.txt?download=true",
        "README.md": "https://huggingface.co/coqui/XTTS-v2/resolve/v2.0.2/README.md?download=true",
        "config.json": "https://huggingface.co/coqui/XTTS-v2/resolve/v2.0.2/config.json?download=true",
        "model.pth": "https://huggingface.co/coqui/XTTS-v2/resolve/v2.0.2/model.pth?download=true",
        "vocab.json": "https://huggingface.co/coqui/XTTS-v2/resolve/v2.0.2/vocab.json?download=true"
    }
}
